{"abstract":"This article explores the opportunities and challenges for dentists in the transition to electronic health records (EHRs). Dentists have been slowed in the digital transition by lack of federal incentives and technical assistance. Now, however, changes in the practice of dentistry, including more integration with other health care providers, may propel them forward.","arxivId":null,"authors":[{"authorId":"2053922018","name":"D. T. Ford","url":"https://www.semanticscholar.org/author/2053922018"}],"citationVelocity":0,"citations":[{"arxivId":null,"authors":[{"authorId":"32221573","name":"Ibrahim Umar Kontagora"},{"authorId":"2418056","name":"I. R. A. Hamid"},{"authorId":"46936475","name":"Nurul Aswa Omar"}],"doi":"10.14569/ijacsa.2019.0100356","intent":["background"],"isInfluential":false,"paperId":"a052b081d8274abeab0be9068ce0d7a57636c101","title":"An Enhanced Concept based Approach for user Centered Health Information Retrieval to Address Readability Issues","url":"https://www.semanticscholar.org/paper/a052b081d8274abeab0be9068ce0d7a57636c101","venue":"International Journal of Advanced Computer Science and Applications","year":2019},{"arxivId":null,"authors":[{"authorId":"2098634638","name":"Zain Chauhan"},{"authorId":"2104708204","name":"M. Samarah"},{"authorId":"143865198","name":"K. Unertl"},{"authorId":"2111039004","name":"Martha Jones"}],"doi":"10.1055/s-0038-1667331","intent":[],"isInfluential":false,"paperId":"d8cfde0c2d516ec70eaf9dff9b1cb0737264c1cd","title":"Adoption of Electronic Dental Records: Examining the Influence of Practice Characteristics on Adoption in One State","url":"https://www.semanticscholar.org/paper/d8cfde0c2d516ec70eaf9dff9b1cb0737264c1cd","venue":"Appl. Clin. Inform.","year":2018},{"arxivId":null,"authors":[{"authorId":"29896777","name":"Yusof Haji Sidek"},{"authorId":"3140051","name":"J. Martins"}],"doi":"10.1016/j.ijmedinf.2017.08.007","intent":[],"isInfluential":false,"paperId":"845ae3f70f6302265640e19fb7513511a7b22466","title":"Perceived critical success factors of electronic health record system implementation in a dental clinic context: An organisational management perspective","url":"https://www.semanticscholar.org/paper/845ae3f70f6302265640e19fb7513511a7b22466","venue":"Int. J. Medical Informatics","year":2017}],"corpusId":36985879,"doi":null,"fieldsOfStudy":["Medicine"],"influentialCitationCount":0,"isOpenAccess":false,"isPublisherLicensed":false,"is_open_access":false,"is_publisher_licensed":false,"numCitedBy":3,"numCiting":0,"paperId":"44186b19b401a66018c0aeb97d9396e04ef61d2c","references":[],"s2FieldsOfStudy":[{"category":"Medicine","source":"external"}],"title":"Are Electronic Health Records the Future of Dental Practice?","topics":[{"topic":"Electronic Health Records","topicId":"21505","url":"https://www.semanticscholar.org/topic/21505"}],"url":"https://www.semanticscholar.org/paper/44186b19b401a66018c0aeb97d9396e04ef61d2c","venue":"Journal of the California Dental Association","year":2015}
